.gitignore
CHANGELOG.rst
LICENSE.txt
MANIFEST.in
README.rst
setup.cfg
setup.py
docs/.gitignore
docs/Makefile
docs/make.bat
docs/source/conf.py
docs/source/index.rst
docs/source/api/modules.rst
docs/source/api/openapilib.rst
openapilib/__init__.py
openapilib/logging_helpers.py
openapilib/spec.py
openapilib/version.py
openapilib.egg-info/PKG-INFO
openapilib.egg-info/SOURCES.txt
openapilib.egg-info/dependency_links.txt
openapilib.egg-info/not-zip-safe
openapilib.egg-info/requires.txt
openapilib.egg-info/top_level.txt