Metadata-Version: 1.2
Name: openapilib
Version: 0.2.1
Summary: OpenAPI 3 object model library
Home-page: https://github.com/joar/py-openapilib
Author: Joar Wandborg
Author-email: joar+pypi@wandborg.se
License: BSD
Keywords: openapi not-swagger
Platform: UNKNOWN
Classifier: License :: OSI Approved :: BSD License
Classifier: Intended Audience :: Developers
Classifier: Development Status :: 4 - Beta
Classifier: Programming Language :: Python :: 3.6
Classifier: Programming Language :: Python :: 3.7
Requires-Python: >=3.6
